mizgra/__init__.py
mizgra/__main__.py
mizgra/config.py
mizgra/outputs/__init__.py
mizgra/outputs/graphml.py
mizgra/outputs/output_format.py
mizgra/outputs/yarspg.py
mizgra/resources/metadata.xml
mizgra/resources/rdf_data.nt
mizgra-1.0.1.dist-info/LICENSE
mizgra-1.0.1.dist-info/METADATA
mizgra-1.0.1.dist-info/WHEEL
mizgra-1.0.1.dist-info/entry_points.txt
mizgra-1.0.1.dist-info/top_level.txt
mizgra-1.0.1.dist-info/RECORD
