Metadata-Version: 2.1
Name: mizgra
Version: 1.0.1
Summary: Converts Mizar ESX MML mathematical data to property graph formats - GraphML, YARS-PG for Neo4j, and other graph databases
Home-page: https://github.com/lszeremeta/mizgra
Author: Łukasz Szeremeta
Author-email: l.szeremeta.dev+mizgra@gmail.com
License: MIT License
Keywords: mizgra,mathematics,parser,CLI,XML,ESX,RDF,MML,Mizar,Mizar Mathematical Library,Mizar Mathematical Library Knowledge Graph,MMLKG,CSV,converter,GraphML,YARS-PG,property graph,graph,graph database,graph data,Neo4j,mathematical data
Classifier: Development Status :: 5 - Production/Stable
Classifier: Environment :: Console
Classifier: Intended Audience :: Education
Classifier: Intended Audience :: Developers
Classifier: Intended Audience :: Information Technology
Classifier: Intended Audience :: Science/Research
Classifier: License :: OSI Approved :: MIT License
Classifier: Natural Language :: English
Classifier: Operating System :: MacOS
Classifier: Operating System :: OS Independent
Classifier: Operating System :: POSIX :: Linux
Classifier: Programming Language :: Python
Classifier: Programming Language :: Python :: 3
Classifier: Programming Language :: Python :: 3 :: Only
Classifier: Programming Language :: Python :: 3.7
Classifier: Programming Language :: Python :: 3.8
Classifier: Programming Language :: Python :: 3.9
Classifier: Programming Language :: Python :: 3.10
Classifier: Programming Language :: Python :: 3.11
Classifier: Topic :: Database
Classifier: Topic :: File Formats
Classifier: Topic :: Internet
Classifier: Topic :: Scientific/Engineering
Classifier: Topic :: Scientific/Engineering :: Information Analysis
Classifier: Topic :: Scientific/Engineering :: Mathematics
Classifier: Topic :: Text Processing
Classifier: Topic :: Text Processing :: General
Classifier: Topic :: Text Processing :: Markup
Classifier: Topic :: Text Processing :: Markup :: XML
Classifier: Topic :: Utilities
Classifier: Typing :: Typed
Requires-Python: >=3.7
License-File: LICENSE
Requires-Dist: importlib-resources >=2.0.0
Requires-Dist: lxml >=4.9.2
Requires-Dist: rdflib >=6.2.0
